odoo10_addon_crm_lead_code-10.0.1.0.0-py2.7-nspkg.pth
odoo/addons/crm_lead_code/README.rst
odoo/addons/crm_lead_code/__init__.py
odoo/addons/crm_lead_code/__manifest__.py
odoo/addons/crm_lead_code/data/lead_sequence.xml
odoo/addons/crm_lead_code/i18n/crm_lead_code.pot
odoo/addons/crm_lead_code/i18n/es.po
odoo/addons/crm_lead_code/models/__init__.py
odoo/addons/crm_lead_code/models/crm_lead.py
odoo/addons/crm_lead_code/static/description/icon.png
odoo/addons/crm_lead_code/tests/__init__.py
odoo/addons/crm_lead_code/tests/test_crm_lead_code.py
odoo/addons/crm_lead_code/views/crm_lead_view.xml
odoo10_addon_crm_lead_code-10.0.1.0.0.dist-info/DESCRIPTION.rst
odoo10_addon_crm_lead_code-10.0.1.0.0.dist-info/METADATA
odoo10_addon_crm_lead_code-10.0.1.0.0.dist-info/RECORD
odoo10_addon_crm_lead_code-10.0.1.0.0.dist-info/WHEEL
odoo10_addon_crm_lead_code-10.0.1.0.0.dist-info/metadata.json
odoo10_addon_crm_lead_code-10.0.1.0.0.dist-info/namespace_packages.txt
odoo10_addon_crm_lead_code-10.0.1.0.0.dist-info/top_level.txt
